axisproj/__init__.py
axisproj/__version__.py
axisproj/axis_aligned.py
axisproj/evidence.py
axisproj/linear.py
axisproj/optimal.py
axisproj/precision_recall.py
axisproj/utils.py
axisproj/objective/__init__.py
axisproj/objective/lde.py
axisproj/objective/lpp.py
axisproj/objective/objective.py
axisproj/objective/pca.py
test/__init__.py
test/test_optimal.py
axisproj-0.2.3.dist-info/LICENSE
axisproj-0.2.3.dist-info/METADATA
axisproj-0.2.3.dist-info/WHEEL
axisproj-0.2.3.dist-info/top_level.txt
axisproj-0.2.3.dist-info/RECORD
