Metadata-Version: 2.1
Name: axisproj
Version: 0.2.3
Summary: Axis-Aligned Decomposition of Linear Projections.
Home-page: https://github.com/yarden-livnat/axisproj
Author: Yarden Livnat
Author-email: yarden@sci.utah.edu
License: BSD 3-Clause
Platform: UNKNOWN
Classifier: License :: OSI Approved :: MIT License
Classifier: Programming Language :: Python
Classifier: Programming Language :: Python :: 3
Classifier: Programming Language :: Python :: 3.6
Classifier: Programming Language :: Python :: Implementation :: CPython
Classifier: Programming Language :: Python :: Implementation :: PyPy
Requires-Python: >=3.7.0
Requires-Dist: numpy
Requires-Dist: sklearn
Requires-Dist: scipy
Requires-Dist: cvxpy
Requires-Dist: nudged
